ai_computer/__init__.py
ai_computer/client.py
ai_computer/models.py
ai_computer/submodules/__init__.py
ai_computer/submodules/base.py
ai_computer/submodules/code.py
ai_computer/submodules/filesystem.py
ai_computer/submodules/shell.py
ai_computer_client-0.3.4.dist-info/METADATA
ai_computer_client-0.3.4.dist-info/WHEEL
ai_computer_client-0.3.4.dist-info/licenses/LICENSE
ai_computer_client-0.3.4.dist-info/RECORD
