Metadata-Version: 2.4
Name: ai-computer-client
Version: 0.3.4
Summary: Python client for interacting with the AI Computer service
Project-URL: Homepage, https://github.com/ColeMurray/ai-computer-client-python
Project-URL: Documentation, https://github.com/ColeMurray/ai-computer-client-python#readme
Author: AI Computer
License: MIT
License-File: LICENSE
Classifier: Development Status :: 4 - Beta
Classifier: Intended Audience :: Developers
Classifier: License :: OSI Approved :: MIT License
Classifier: Programming Language :: Python :: 3
Classifier: Programming Language :: Python :: 3.7
Classifier: Programming Language :: Python :: 3.8
Classifier: Programming Language :: Python :: 3.9
Classifier: Programming Language :: Python :: 3.10
Classifier: Programming Language :: Python :: 3.11
Requires-Python: >=3.7
Requires-Dist: aiohttp>=3.8.0
Requires-Dist: typing-extensions>=4.0.0
Provides-Extra: dev
Requires-Dist: pytest-asyncio>=0.21.0; extra == 'dev'
Requires-Dist: pytest-cov>=4.0.0; extra == 'dev'
Requires-Dist: pytest>=7.0.0; extra == 'dev'
Provides-Extra: integration
Requires-Dist: pytest-asyncio>=0.21.0; extra == 'integration'
Requires-Dist: pytest>=7.0.0; extra == 'integration'
